<?xml version="1.0" encoding="utf-8" ?>
<dwsync>
<file name="background.gif" server="W:/" local="129122017800000000" remote="129122017800000000" Dst="2" />
<file name="topbg.gif" server="W:/" local="129121708280000000" remote="129121708280000000" Dst="2" />
<file name="navbar-left.gif" server="W:/" local="129121204600000000" remote="129121204600000000" Dst="2" />
<file name="navbar-right.gif" server="W:/" local="129121204800000000" remote="129121204800000000" Dst="2" />
<file name="navbar-bg.gif" server="W:/" local="129121205380000000" remote="129121205380000000" Dst="2" />
<file name="navbar-divider.gif" server="W:/" local="129121205840000000" remote="129121205840000000" Dst="2" />
<file name="header.jpg" server="W:/" local="130343283170000000" remote="130343283170000000" Dst="2" />
<file name="body-bg.gif" server="W:/" local="129121770860000000" remote="129121770860000000" Dst="2" />
<file name="body-divider.gif" server="W:/" local="129121209200000000" remote="129121209200000000" Dst="2" />
<file name="headline-arrow.gif" server="W:/" local="129122001120000000" remote="129122001120000000" Dst="2" />
<file name="content-divider.gif" server="W:/" local="129121210660000000" remote="129121210660000000" Dst="2" />
<file name="submit.gif" server="W:/" local="129127003020000000" remote="129127003020000000" Dst="2" />
<file name="footer-div.gif" server="W:/" local="129122007660000000" remote="129122007660000000" Dst="2" />
<file name="network_issue_fix.png" server="W:/" local="130421950420000000" remote="130421950420000000" Dst="2" />
<file name="background.gif" server="x:/" local="129121981800000000" remote="129121981800000000" Dst="2" />
<file name="topbg.gif" server="x:/" local="129121672280000000" remote="129121672280000000" Dst="2" />
<file name="navbar-left.gif" server="x:/" local="129121168600000000" remote="129121168600000000" Dst="2" />
<file name="navbar-right.gif" server="x:/" local="129121168800000000" remote="129121168800000000" Dst="2" />
<file name="navbar-bg.gif" server="x:/" local="129121169380000000" remote="129121169380000000" Dst="2" />
<file name="navbar-divider.gif" server="x:/" local="129121169840000000" remote="129121169840000000" Dst="2" />
<file name="header.jpg" server="x:/" local="130343247180000000" remote="130343247180000000" Dst="2" />
<file name="body-bg.gif" server="x:/" local="129121734860000000" remote="129121734860000000" Dst="2" />
<file name="body-divider.gif" server="x:/" local="129121173200000000" remote="129121173200000000" Dst="2" />
<file name="headline-arrow.gif" server="x:/" local="129121965120000000" remote="129121965120000000" Dst="2" />
<file name="content-divider.gif" server="x:/" local="129121174660000000" remote="129121174660000000" Dst="2" />
<file name="submit.gif" server="x:/" local="129126967020000000" remote="129126967020000000" Dst="2" />
<file name="footer-div.gif" server="x:/" local="129121971660000000" remote="129121971660000000" Dst="2" />
<file name="Ballpoint-Pen-Biro1.jpg" server="x:/" local="130344794440000000" remote="130344794440000000" Dst="1" />
<file name="Pencil3.png" server="x:/" local="130344786360000000" remote="130344786360000000" Dst="1" />
<file name="linedpaper.png" server="x:/" local="130344796260000000" remote="130344796260000000" Dst="1" />
<file name="IMG_20140226_085944.jpg" server="x:/" local="130378391860000000" remote="130378391860000000" Dst="1" />
<file name="IMG_20140226_085959.jpg" server="x:/" local="130378392000000000" remote="130378392000000000" Dst="1" />
<file name="Tools_for_video_making.png" server="x:/" local="130372036680000000" remote="130372036680000000" Dst="1" />
<file name="designcycle_aa.jpg" server="W:/" local="130500506140000000" remote="130500506140000000" Dst="2" />
<file name="adameyiletenwebsitethumbnail.JPG" server="W:/" local="130656825520000000" remote="130656825520000000" Dst="2" />
<file name="arianjahiriwebsitethumbnail.JPG" server="W:/" local="130656825640000000" remote="130656825640000000" Dst="2" />
<file name="Ballpoint-Pen-Biro1.jpg" server="W:/" local="130344794430000000" remote="130344794430000000" Dst="2" />
<file name="dankifluwebsitethumbnail.JPG" server="W:/" local="130656830060000000" remote="130656830060000000" Dst="2" />
<file name="DEClogin.png" server="W:/" local="130344786210000000" remote="130344786210000000" Dst="2" />
<file name="google_license_search.JPG" server="W:/" local="130344840170000000" remote="130344840170000000" Dst="2" />
<file name="html5_codec_setting.png" server="W:/" local="130403171300000000" remote="130403171300000000" Dst="2" />
<file name="IMG_20140226_085944.jpg" server="W:/" local="130378391850000000" remote="130378391850000000" Dst="2" />
<file name="IMG_20140226_085959.jpg" server="W:/" local="130378392000000000" remote="130378392000000000" Dst="2" />
<file name="linedpaper.png" server="W:/" local="130344796260000000" remote="130344796260000000" Dst="2" />
<file name="micro-usb-cable-1.jpg" server="W:/" local="130344786260000000" remote="130344786260000000" Dst="2" />
<file name="Pencil3.png" server="W:/" local="130344786360000000" remote="130344786360000000" Dst="2" />
<file name="Philips-SHE9850-earphones_1.jpg" server="W:/" local="130344786150000000" remote="130344786150000000" Dst="2" />
<file name="ReadyToLearn_logo.png" server="W:/" local="130344792870000000" remote="130344792870000000" Dst="2" />
<file name="spacer.gif" server="W:/" local="129127020560000000" remote="129127020560000000" Dst="2" />
<file name="Tools_for_video_making.png" server="W:/" local="130372036670000000" remote="130372036670000000" Dst="2" />
<file name="adameyiletenwebsitethumbnail.JPG" server="D:/Shares/Website/" local="130656825520000000" remote="130656825520000000" Dst="2" />
<file name="arianjahiriwebsitethumbnail.JPG" server="D:/Shares/Website/" local="130656825640000000" remote="130656825640000000" Dst="2" />
<file name="background.gif" server="D:/Shares/Website/" local="129122017800000000" remote="129122017800000000" Dst="2" />
<file name="Ballpoint-Pen-Biro1.jpg" server="D:/Shares/Website/" local="130344794430000000" remote="130344794430000000" Dst="2" />
<file name="body-bg.gif" server="D:/Shares/Website/" local="129121770860000000" remote="129121770860000000" Dst="2" />
<file name="body-divider.gif" server="D:/Shares/Website/" local="129121209200000000" remote="129121209200000000" Dst="2" />
<file name="content-divider.gif" server="D:/Shares/Website/" local="129121210660000000" remote="129121210660000000" Dst="2" />
<file name="dankifluwebsitethumbnail.JPG" server="D:/Shares/Website/" local="130656830060000000" remote="130656830060000000" Dst="2" />
<file name="DEClogin.png" server="D:/Shares/Website/" local="130344786210000000" remote="130344786210000000" Dst="2" />
<file name="designcycle_aa.jpg" server="D:/Shares/Website/" local="130500506140000000" remote="130500506140000000" Dst="2" />
<file name="footer-div.gif" server="D:/Shares/Website/" local="129122007660000000" remote="129122007660000000" Dst="2" />
<file name="google_license_search.JPG" server="D:/Shares/Website/" local="130344840170000000" remote="130344840170000000" Dst="2" />
<file name="header.jpg" server="D:/Shares/Website/" local="130343283170000000" remote="130343283170000000" Dst="2" />
<file name="headline-arrow.gif" server="D:/Shares/Website/" local="129122001120000000" remote="129122001120000000" Dst="2" />
<file name="html5_codec_setting.png" server="D:/Shares/Website/" local="130403171300000000" remote="130403171300000000" Dst="2" />
<file name="IMG_20140226_085944.jpg" server="D:/Shares/Website/" local="130378391850000000" remote="130378391850000000" Dst="2" />
<file name="IMG_20140226_085959.jpg" server="D:/Shares/Website/" local="130378392000000000" remote="130378392000000000" Dst="2" />
<file name="linedpaper.png" server="D:/Shares/Website/" local="130344796260000000" remote="130344796260000000" Dst="2" />
<file name="micro-usb-cable-1.jpg" server="D:/Shares/Website/" local="130344786260000000" remote="130344786260000000" Dst="2" />
<file name="navbar-bg.gif" server="D:/Shares/Website/" local="129121205380000000" remote="129121205380000000" Dst="2" />
<file name="navbar-divider.gif" server="D:/Shares/Website/" local="129121205840000000" remote="129121205840000000" Dst="2" />
<file name="navbar-left.gif" server="D:/Shares/Website/" local="129121204600000000" remote="129121204600000000" Dst="2" />
<file name="navbar-right.gif" server="D:/Shares/Website/" local="129121204800000000" remote="129121204800000000" Dst="2" />
<file name="network_issue_fix.png" server="D:/Shares/Website/" local="130421950420000000" remote="130421950420000000" Dst="2" />
<file name="Pencil3.png" server="D:/Shares/Website/" local="130344786360000000" remote="130344786360000000" Dst="2" />
<file name="Philips-SHE9850-earphones_1.jpg" server="D:/Shares/Website/" local="130344786150000000" remote="130344786150000000" Dst="2" />
<file name="ReadyToLearn_logo.png" server="D:/Shares/Website/" local="130344792870000000" remote="130344792870000000" Dst="2" />
<file name="spacer.gif" server="D:/Shares/Website/" local="129127020560000000" remote="129127020560000000" Dst="2" />
<file name="submit.gif" server="D:/Shares/Website/" local="129127003020000000" remote="129127003020000000" Dst="2" />
<file name="Tools_for_video_making.png" server="D:/Shares/Website/" local="130372036670000000" remote="130372036670000000" Dst="2" />
<file name="topbg.gif" server="D:/Shares/Website/" local="129121708280000000" remote="129121708280000000" Dst="2" />
</dwsync>